volttrontesting/__init__.py
volttrontesting/agent_additions.py
volttrontesting/certs_utils.py
volttrontesting/client_mock.py
volttrontesting/fixtures/__init__.py
volttrontesting/fixtures/cert_fixtures.py
volttrontesting/fixtures/docker_wrapper.py
volttrontesting/fixtures/rmq_test_setup.py
volttrontesting/fixtures/volttron_platform_fixtures.py
volttrontesting/memory_pubsub.py
volttrontesting/messagebus_factory.py
volttrontesting/mock_agent.py
volttrontesting/mock_agent_factory.py
volttrontesting/mock_connection.py
volttrontesting/mock_core.py
volttrontesting/mock_core_builder.py
volttrontesting/mock_messagebus.py
volttrontesting/mock_process_agent.py
volttrontesting/mock_pubsub_subsystem.py
volttrontesting/platformwrapper.py
volttrontesting/platformwrapper_enhanced.py
volttrontesting/pubsub_interceptor.py
volttrontesting/server_mock.py
volttrontesting/testing_context.py
volttrontesting/utils.py
volttron_testing-0.5.1rc4.dist-info/LICENSE
volttron_testing-0.5.1rc4.dist-info/METADATA
volttron_testing-0.5.1rc4.dist-info/WHEEL
volttron_testing-0.5.1rc4.dist-info/RECORD
