Metadata-Version: 2.3
Name: volttron-testing
Version: 0.5.1rc4
Summary: The volttron-testing library contains classes and utilities for interacting with a VOLTTRON instance.
License: Apache-2.0
Author: VOLTTRON Team
Author-email: volttron@pnnl.gov
Requires-Python: >=3.10,<4.0
Classifier: Intended Audience :: Developers
Classifier: Intended Audience :: Information Technology
Classifier: Intended Audience :: Other Audience
Classifier: Intended Audience :: Science/Research
Classifier: License :: OSI Approved :: Apache Software License
Classifier: Programming Language :: Python :: 3
Classifier: Programming Language :: Python :: 3.10
Classifier: Programming Language :: Python :: 3.11
Classifier: Programming Language :: Python :: 3.12
Classifier: Programming Language :: Python :: 3.13
Classifier: Programming Language :: Python :: 3 :: Only
Requires-Dist: anypubsub (>=0.6,<0.7)
Requires-Dist: docker (>=6.0.1,<7.0.0)
Requires-Dist: grequests (>=0.6.0,<0.7.0)
Requires-Dist: pytest (>=7.0.0,<8.0.0)
Requires-Dist: pytest-timeout (>=2.3.1,<3.0.0)
Requires-Dist: python-dateutil (>=2.8.2,<3.0.0)
Requires-Dist: volttron-core (>=2.0.0rc16)
Requires-Dist: volttron-lib-auth (>=2.0.0rc6)
Project-URL: Homepage, https://github.com/eclipse-volttron/volttron-testing
Project-URL: Repository, https://github.com/eclipse-volttron/volttron-testing
